orkgnlp/__init__.py
orkgnlp/annotation/__init__.py
orkgnlp/annotation/agriner/__init__.py
orkgnlp/annotation/agriner/annotator.py
orkgnlp/annotation/agriner/decoder.py
orkgnlp/annotation/csner/__init__.py
orkgnlp/annotation/csner/annotator.py
orkgnlp/annotation/csner/decoder.py
orkgnlp/annotation/csner/encoder.py
orkgnlp/annotation/rfclf/__init__.py
orkgnlp/annotation/rfclf/classifier.py
orkgnlp/annotation/rfclf/decoder.py
orkgnlp/annotation/rfclf/encoder.py
orkgnlp/annotation/tdm/__init__.py
orkgnlp/annotation/tdm/decoder.py
orkgnlp/annotation/tdm/encoder.py
orkgnlp/annotation/tdm/extractor.py
orkgnlp/clustering/__init__.py
orkgnlp/clustering/bioassays/__init__.py
orkgnlp/clustering/bioassays/decoder.py
orkgnlp/clustering/bioassays/semantifier.py
orkgnlp/clustering/encoders.py
orkgnlp/clustering/predicates/__init__.py
orkgnlp/clustering/predicates/decoder.py
orkgnlp/clustering/predicates/recommender.py
orkgnlp/common/__init__.py
orkgnlp/common/config/__init__.py
orkgnlp/common/config/context.py
orkgnlp/common/service/__init__.py
orkgnlp/common/service/base.py
orkgnlp/common/service/runners.py
orkgnlp/common/tools/__init__.py
orkgnlp/common/tools/downloader.py
orkgnlp/common/tools/loader.py
orkgnlp/common/util/__init__.py
orkgnlp/common/util/datastructure.py
orkgnlp/common/util/decorators.py
orkgnlp/common/util/exceptions.py
orkgnlp/common/util/io.py
orkgnlp/common/util/text.py
orkgnlp/huggingface_repos.json
orkgnlp/huggingface_repos_schema.json
orkgnlp/nli/__init__.py
orkgnlp/nli/templates/__init__.py
orkgnlp/nli/templates/decoder.py
orkgnlp/nli/templates/encoder.py
orkgnlp/nli/templates/recommender.py
orkgnlp-1.0.1.dist-info/METADATA
orkgnlp-1.0.1.dist-info/WHEEL
orkgnlp-1.0.1.dist-info/entry_points.txt
orkgnlp-1.0.1.dist-info/licenses/LICENSE
orkgnlp-1.0.1.dist-info/RECORD
