Metadata-Version: 2.4
Name: orkgnlp
Version: 1.0.1
Summary: Python package wrapping the ORKG NLP Services.
License: MIT
License-File: LICENSE
Keywords: ORKG,NLP,Scholarly Communication,Digital Library
Author: Omar Arab Oghli
Author-email: omar.araboghli@outlook.com
Maintainer: Hamed Babaei Giglou
Maintainer-email: hamedbabaeigiglou@gmail.com
Requires-Python: >=3.11,<3.14
Classifier: License :: OSI Approved :: MIT License
Classifier: Programming Language :: Python :: 3
Classifier: Programming Language :: Python :: 3.11
Classifier: Programming Language :: Python :: 3.12
Classifier: Programming Language :: Python :: 3.13
Requires-Dist: huggingface-hub (>=0.34.4,<0.35.0)
Requires-Dist: nltk (>=3.9.1,<4.0.0)
Requires-Dist: numpy (>=2.3.3,<3.0.0)
Requires-Dist: onnx (>=1.19.0,<2.0.0)
Requires-Dist: onnxruntime (>=1.22.1,<2.0.0)
Requires-Dist: overrides (>=7.7.0,<8.0.0)
Requires-Dist: pandas (>=2.3.2,<3.0.0)
Requires-Dist: pre-commit (>=4.3.0,<5.0.0)
Requires-Dist: protobuf (>=6.32.1,<7.0.0)
Requires-Dist: sentence-transformers (>=5.1.0,<6.0.0)
Requires-Dist: sentencepiece (>=0.2.1,<0.3.0)
Requires-Dist: spacy (>=3.8.7,<4.0.0)
Requires-Dist: torch (>=2.8.0,<3.0.0)
Requires-Dist: transformers (>=4.56.1,<5.0.0)
Requires-Dist: typing-extensions (>=4.15.0,<5.0.0)
Project-URL: Documentation, https://orkg-nlp-pypi.readthedocs.io/en/latest/
Project-URL: Homepage, http://orkg.org/about
Project-URL: Repository, https://gitlab.com/TIBHannover/orkg/nlp/orkg-nlp-pypi
